hemabot/__init__.py
hemabot/api.py
hemabot/auth.py
hemabot/config.py
hemabot/processors/__init__.py
hemabot/processors/base.py
hemabot/processors/deepl.py
hemabot/processors/oncemessager.py
hemabot/processors/twitter.py
hemabot-0.0.3.dist-info/METADATA
hemabot-0.0.3.dist-info/WHEEL
hemabot-0.0.3.dist-info/entry_points.txt
hemabot-0.0.3.dist-info/top_level.txt
hemabot-0.0.3.dist-info/RECORD
